sourced/__init__.py
sourced/__main__.py
sourced/analyze.py
sourced/_internal/__init__.py
sourced/_internal/parallelization.py
sourced/dataset/__init__.py
sourced/dataset/__main__.py
sourced/dataset/db.py
sourced/dataset/pypi.py
sourced-0.1.0.dist-info/METADATA
sourced-0.1.0.dist-info/WHEEL
sourced-0.1.0.dist-info/entry_points.txt
sourced-0.1.0.dist-info/top_level.txt
sourced-0.1.0.dist-info/RECORD
