Metadata-Version: 2.1
Name: sourced
Version: 0.1.0
Summary: Tooling around mass-scale Python source code analysis.
Home-page: https://github.com/isidentical/sourced
Author: isidentical
Author-email: isidentical@gmail.com
License: MIT
Project-URL: Source, https://github.com/isidentical/sourced
Project-URL: Tracker, https://github.com/isidentical/sourced/issues
Classifier: License :: OSI Approved :: MIT License
Classifier: Programming Language :: Python :: 3
Classifier: Programming Language :: Python :: 3 :: Only
Classifier: Programming Language :: Python :: 3.9
Classifier: Programming Language :: Python :: 3.10
Classifier: Programming Language :: Python :: 3.11
Requires-Python: >=3.9
Requires-Dist: platformdirs (>=2.4.0)
Requires-Dist: rich (>=12.0.0)
